{"cameraMode":{"drawMode":0,"name":"Shaded","section":"Shading Mode"},"sceneLighting":true,"audioPlay":false,"sceneViewState":{"showFog":true,"showMaterialUpdate":false,"showSkybox":true,"showFlares":true,"showImageEffects":true,"showParticleSystems":true},"in2DMode":false,"pivot":{"x":199.36080932617188,"y":112.99263000488281,"z":230.9877166748047},"rotation":{"x":0.03344978019595146,"y":0.966458797454834,"z":-0.18668074905872346,"w":0.17317283153533936},"size":61.29656219482422,"orthographic":false}